django_table_widgets/__init__.py
django_table_widgets/fields.py
django_table_widgets/static/django_table_widgets/js/TableFieldSum.js
django_table_widgets/templates/django_table_widgets/widgets/row.html
django_table_widgets/templates/django_table_widgets/widgets/row_sum.html
django_table_widgets/templates/django_table_widgets/widgets/table.html
django_table_widgets/widgets.py
django_table_widgets-0.0.2.dist-info/LICENSE
django_table_widgets-0.0.2.dist-info/METADATA
django_table_widgets-0.0.2.dist-info/WHEEL
django_table_widgets-0.0.2.dist-info/RECORD
