Metadata-Version: 2.3
Name: django-table-widgets
Version: 0.0.2
Summary: Widgets to display and edit two-dimensionals ArrayFields, based on django's `SplitArrayField`.
License: BSD-3-Clause
Author: Kapt
Author-email: dev@kapt.mobi
Requires-Python: >=3.10
Classifier: License :: OSI Approved :: BSD License
Classifier: Programming Language :: Python :: 3
Classifier: Programming Language :: Python :: 3.10
Classifier: Programming Language :: Python :: 3.11
Classifier: Programming Language :: Python :: 3.12
Classifier: Programming Language :: Python :: 3.13
Requires-Dist: Django (>=3.0)
Project-URL: Repository, https://gitlab.com/kapt/open-source/django-table-widgets
